odoo/addons/modify_followers_task/README.rst
odoo/addons/modify_followers_task/__init__.py
odoo/addons/modify_followers_task/__manifest__.py
odoo/addons/modify_followers_task/i18n/es.po
odoo/addons/modify_followers_task/security/ir.model.access.csv
odoo/addons/modify_followers_task/static/description/icon.png
odoo/addons/modify_followers_task/views/project_task_view.xml
odoo/addons/modify_followers_task/wizard/__init__.py
odoo/addons/modify_followers_task/wizard/modify_followers_task_wizard.py
odoo/addons/modify_followers_task/wizard/modify_followers_task_wizard.xml
odoo_addon_modify_followers_task-15.0.1.0.0.2.dist-info/METADATA
odoo_addon_modify_followers_task-15.0.1.0.0.2.dist-info/WHEEL
odoo_addon_modify_followers_task-15.0.1.0.0.2.dist-info/top_level.txt
odoo_addon_modify_followers_task-15.0.1.0.0.2.dist-info/RECORD
