Metadata-Version: 2.1
Name: odoo-addon-modify_followers_task
Version: 15.0.1.0.0.2
Requires-Python: >=3.8
Requires-Dist: odoo>=15.0a,<15.1dev
Summary: Modify list of followers from a project task
Home-page: https://github.com/sygel-technology/sy-project
License: AGPL-3
Author: QubiQ, Odoo Community Association (OCA)
Author-email: support@odoo-community.org
Classifier: Programming Language :: Python
Classifier: Framework :: Odoo
Classifier: Framework :: Odoo :: 15.0
Classifier: License :: OSI Approved :: GNU Affero General Public License v3
